[
  {
    "id": "USR-123",
    "avatar": "https://connectedapp20200512063146.azurewebsites.net/api/connectedadmin/GetImage/b6ba9520-0ad8-4630-9d02-0cfa61bc58dc.jpeg",
    "name": "Mohamed Abdelghany",
    "email": "mohamedabdelghanyy@gmail.com",
    "mobile": "+201115696965",
    "birthdate": "21/01/1950",
    "gender": "Female",
    "country": "Egypt",
    "address": "Degla El Maadi",
    "occupation": "Dev.",
    "company": "Connected",
    "customerType": "Top VIP",
    "noofposts": 9,
    "noofwishlist": 20,
    "lastseen": "18/08/2023",
    "interests": "Automotive",
    "source": "invitation",
    "status": "approved"
  },
  {
    "id": "USR-456",
    "avatar": "https://connectedapp20200512063146.azurewebsites.net/api/connectedadmin/GetImage/6bcf548f-dffa-4218-a109-f27ddcb30317.jpg",
    "name": "Soha Elhadary",
    "email": "sohaelhadary@gmail.com",
    "mobile": "+201224466880",
    "birthdate": "21/01/1950",
    "gender": "Male",
    "country": "Egypt",
    "address": "3ezbet el nakhl",
    "occupation": "Project Manager",
    "company": "Connected",
    "customerType": "Regular",
    "noofposts": 23,
    "noofwishlist": 32,
    "lastseen": "16/08/2023",
    "interests": "Lifestyle",
    "source": "leads",
    "status": "rejected"
  },
  {
    "id": "USR-789",
    "avatar": "",
    "name": "Khaled Afify",
    "email": "khaledafify@gmail.com",
    "mobile": "+201234567890",
    "birthdate": "21/01/1950",
    "gender": "Male",
    "country": "SA",
    "address": "Makkah",
    "occupation": "Senior Dev.",
    "company": "Connected",
    "customerType": "VIP",
    "noofposts": 19,
    "noofwishlist": 11,
    "lastseen": "16/08/2023",
    "interests": "Realestate",
    "source": "registration",
    "status": "pending"
  }
]